[{"sent": ["I", "ca", "n't", "imagine", "a", "better-written", "treatment", "of", "the", "subject", "."], "pred": [["the article overall", "it", "positive", "better"]], "gold": [["the content plot", "subject", "positive", "can't imagine a better-written"]]}, {"sent": ["I", "really", "like", "it.Be", "forewarned", "(", "as", "other", "reviews", "have", "noted", ")", ",", "this", "book", "sets", "up", "Magician", "'s", "End", "and", "you", "will", "not", "be", "particularly", "satisfied", "with", "the", "ending", "without", "keeping", "this", "in", "mind", "."], "pred": [["the book overall", "it", "positive", "like"], ["the book overall", "Magician's End", "negative", "not particularly satisfied"]], "gold": [["the book overall", "book", "positive", "really like"], ["the content plot", "ending", "negative", "not be particularly satisfied"]]}, {"sent": ["A", "mix", "of", "the", "Christian", "beliefs", "mixed", "with", "sexual", "abuse", ",", "followed", "by", "a", "courageous", "exit", "."], "pred": [["the ambience", "it", "negative", "mixed"], ["the service", "it", "positive", "courageous"]], "gold": [["the content plot", "it", "positive", "courageous"]]}, {"sent": ["If", "you", "'re", "into", "Diana", "books", "I", "'d", "keep", "this", "one", "last", "after", "you", "'ve", "read", "the", "rest", "."], "pred": [["the restaurant overall", "it", "positive", "NULL"]], "gold": [["the book overall", "it", "positive", "NULL"]]}, {"sent": ["The", "truth", "is", ",", "I", "felt", "the", "character", "'s", "journey", "was", "really", "a", "tough", "one", "to", "plod", "through", "at", "points", ",", "but", "ultimately", "satifying", "."], "pred": [["the character", "character", "positive", "tough"], ["the character", "character", "positive", "satifying"]], "gold": [["the content plot", "character's journey", "positive", "ultimately satifying"]]}, {"sent": ["OMG", "this", "book", "had", "my", "head", "spinning", "."], "pred": [["the book overall", "book", "negative", "NULL"]], "gold": [["the book overall", "book", "positive", "NULL"]]}, {"sent": ["Still", ",", "it", "was", "good", "to", "finish", "the", "series", "finally", "and", "there", "was", "some", "escape", "into", "the", "magical", "world", "...", "just", "not", "as", "much", "fun", "to", "read", "as", "I", "had", "hoped", "."], "pred": [["the book overall", "it", "positive", "good"], ["the ambience", "magical world", "positive", "escape"], ["the book overall", "it", "negative", "not as much fun"]], "gold": [["the book overall", "series", "positive", "good"], ["the content plot", "it", "negative", "not as much fun"]]}, {"sent": ["And", "while", "not", "being", "at", "all", "didactic", "in", "the", "patronizing", "sense", ",", "the", "book", "teaches", "the", "reader", "a", "great", "deal", "about", "cancer", "the", "disease", "and", "its", "treatment", "."], "pred": [["the book overall", "it", "positive", "didactic"]], "gold": [["the book overall", "book", "positive", "NULL"]]}, {"sent": ["Highly", "recommend", "this", "book", "."], "pred": [["the book overall", "book", "positive", "recommend"]], "gold": [["the book overall", "book", "positive", "highly recommend"]]}, {"sent": ["However", ",", "if", "you", "want", "more", "details", "about", "the", "man", "in", "general", ",", "his", "family", ",", "his", "struggles", "over", "the", "years", ",", "then", "I", "would", "suggest", "Roasting", "in", "Hell", "'s", "Kitchen", "."], "pred": [["the restaurant overall", "man", "negative", "NULL"], ["the restaurant overall", "roasting in hell's kitchen", "positive", "NULL"]], "gold": [["the book characters", "roasting in hell's kitchen", "positive", "NULL"]]}, {"sent": ["There", "is", "also", "the", "issue", "of", "whether", "various", "treatments", "were", "actually", "extending", "the", "lifespans", "of", "those", "afflicted", ",", "which", "was", "also", "not", "as", "simple", "as", "one", "might", "think.While", "the", "above", "discussion", "of", "science", "and", "statistics", "might", "make", "this", "book", "seem", "dreadfully", "boring", ",", "this", "is", "n't", "the", "case", "."], "pred": [["the book overall", "it", "negative", "boring"], ["the science and statistics", "it", "negative", "not as simple"]], "gold": [["the content overall", "book", "neutral", "seem dreadfully boring, this isn't the case"]]}, {"sent": ["Here", ",", "we", "see", "that", "aspect", "of", "the", "tale", "really", "expanded", "upon", ",", "elevating", "a", "lackluster", "minor", "plot", "thread", "to", "a", "level", "of", "significance", "worthy", "of", "Midkemia", "'s", "final", "chapter", "."], "pred": [["the storyline", "plot thread", "negative", "lackluster"], ["the book overall", "it", "positive", "NULL"]], "gold": [["the content plot", "tale", "positive", "really expanded upon"], ["the content plot", "plot thread", "negative", "lackluster minor"], ["the content plot", "plot", "positive", "level of significance"]]}, {"sent": ["The", "writing", "in", "particular", "is", "disapointing", ":", "unsophisticated", ",", "almost", "juvenile", "in", "comparison", "to", "earlier", "volumes", "."], "pred": [["the language quality", "writing", "negative", "disapointing"], ["the language styles and options", "writing", "negative", "unsophisticated"], ["the writing quality", "writing", "negative", "juvenile"]], "gold": [["the content quality", "writing", "negative", "disapointing : unsophisticated, almost juvenile"]]}, {"sent": ["Loved", "the", "book", "."], "pred": [["the book overall", "book", "positive", "loved"]], "gold": [["the book overall", "book", "positive", "loved"]]}, {"sent": ["Sad", "tale", "of", "just", "how", "easy", "it", "is", "for", "these", "abused", "children", "to", "get", "lost", "in", "the", "welfare", "system", "."], "pred": [["the situation", "children", "negative", "abused"]], "gold": [["the content plot", "sad tale", "neutral", "NULL"]]}, {"sent": ["And", "then", "we", "about", "hit", "rock", "bottom", "with", "The", "Demonwar", "Saga", "."], "pred": [["the movie overall", "Demonwar Saga", "negative", "NULL"]], "gold": [["the book overall", "the demonwar saga", "negative", "hit rock bottom"]]}, {"sent": ["Not", "that", "there", "is", "no", "humour", "the", "author", "has", "the", "ability", "to", "bring", "an", "ironic", "touch", "to", "the", "darkest", "scenes", "but", "this", "is", "not", "a", "crime", "novel", "for", "the", "faint", "hearted", "."], "pred": [["the humour", "author", "positive", "NULL"], ["the author's ability to bring an ironic touch to the darkest scenes", "it", "negative", "NULL"]], "gold": [["the content genre", "crime novel", "positive", "NULL"]]}, {"sent": ["The", "3", "lady", "'s", "courage", "can", "be", "found", "to", "be", "inspirational", "&", "a", "lesson", "to", "us", "all", "."], "pred": [["the service", "it", "positive", "inspirational"], ["the service", "it", "positive", "lesson"]], "gold": [["the content characters", "3 lady's courage", "positive", "inspirational"]]}, {"sent": ["For", "an", "avid", "Diana", "fan", ",", "the", "innocent", "day-to-day", "insight", "is", "appreciated", ",", "however", ",", "certain", "facts", "should", "not", "have", "been", "revealed", "."], "pred": [["the journalistic quality", "it", "positive", "appreciated"], ["the journalistic integrity", "it", "negative", "NULL"]], "gold": [["the content quality", "innocent day-to-day insight", "positive", "appreciated"]]}, {"sent": ["I", "have", "had", "this", "on", "my", "shelf", "for", "several", "years", "for", "intended", "reading", ":", "Had", "I", "appreciated", "what", "a", "compelling", "narrative", "Mukherjee", "sets", "out", ",", "and", "how", "well", "he", "tells", "it", ",", "I", "would", "have", "read", "it", "much", "sooner.As", "there", "are", "numerous", ",", "good", "reviews", "of", "this", "exceptional", "book", ",", "I", "will", "not", "pile", "on", ",", "except", "to", "say", "that", "this", "is", "a", "comprehensive", "and", "detailed", "treatment", "for", "the", "non-expert", ",", "that", "manages", "to", "explain", "the", "science", "(", "and", "some", "of", "the", "politics", ")", "with", "clarity", ",", "while", "providing", "a", "compelling", "and", "often", "moving", "narrative", "."], "pred": [["the book overall", "it", "positive", "exceptional"], ["the book's contents", "it", "positive", "comprehensive"], ["the writing style", "it", "positive", "detailed"], ["the reading experience", "it", "positive", "compelling"], ["the reading experience", "it", "positive", "moving"]], "gold": [["the content quality", "narrative", "positive", "compelling"], ["the book overall", "book", "positive", "exceptional"], ["the content quality", "narrative", "positive", "compelling and often moving"]]}, {"sent": ["The", "location", "is", "unbeatable", "and", "the", "rooftop", "was", "beyond", "spectacular", "."], "pred": [["the location", "location", "positive", "unbeatable"], ["the ambience", "rooftop", "positive", "spectacular"]], "gold": [["the location overall", "location", "positive", "unbeatable"], ["the facilities features", "rooftop", "positive", "beyond spectacular"]]}, {"sent": ["The", "room", "was", "very", "comfortable", "and", "the", "bathroom", "connected", "to", "the", "room", "was", "a", "great", "addition", "."], "pred": [["the ambience", "room", "positive", "comfortable"], ["the ambience", "bathroom", "positive", "great"]], "gold": [["the rooms comfort", "room", "positive", "very comfortable"], ["the room_amenities overall", "bathroom", "positive", "great addition"]]}, {"sent": ["It", "'s", "a", "good", "place", "and", "will", "definitely", "consider", "to", "come", "again", "."], "pred": [["the restaurant overall", "place", "positive", "good"]], "gold": [["the hotel overall", "place", "positive", "good"]]}, {"sent": ["There", "is", "a", "grocery", "store", "a", "15", "min", "walk", "away", ",", "which", "was", "easy", "to", "walk", "from", "with", "a", "few", "groceries", "for", "breakfasts", "and", "snacks", "."], "pred": [["the location", "grocery store", "positive", "easy"]], "gold": [["the location overall", "grocery store", "positive", "easy to walk"]]}, {"sent": ["The", "apartment", "is", "kept", "very", "clean", ",", "and", "nicely", "furnished", "."], "pred": [["the ambience", "apartment", "positive", "clean"], ["the ambience", "apartment", "positive", "nicely furnished"]], "gold": [["the rooms cleanliness", "apartment", "positive", "very clean"], ["the rooms features", "apartment", "positive", "nicely furnished"]]}, {"sent": ["Really", "great", "location", "close", "to", "so", "many", "restaurants", "."], "pred": [["the location", "location", "positive", "great"]], "gold": [["the location overall", "location", "positive", "really great"]]}, {"sent": ["Oine", "was", "a", "terrific", "host", "-", "very", "responsive", "by", "text", "and", "email", ",", "and", "thoughtful", "with", "her", "preparation", "of", "the", "apartment", ",", "which", "was", "spotless", "and", "nicely", "decorated", ",", "and", "feels", "like", "home", "."], "pred": [["the service", "host", "positive", "terrific"], ["the service", "host", "positive", "responsive"], ["the service", "apartment", "positive", "thoughtful"], ["the ambience", "apartment", "positive", "spotless"], ["the ambience", "apartment", "positive", "nicely decorated"]], "gold": [["the service overall", "host", "positive", "terrific"], ["the service quality", "host", "positive", "very responsive"], ["the service overall", "host", "positive", "thoughtful"], ["the rooms cleanliness", "apartment", "positive", "spotless"], ["the rooms features", "apartment", "positive", "nicely decorated"]]}, {"sent": ["Excellent", "space", "in", "a", "fantastic", "location", "."], "pred": [["the ambience", "space", "positive", "excellent"], ["the location", "location", "positive", "fantastic"]], "gold": [["the rooms features", "space", "positive", "excellent"], ["the location overall", "location", "positive", "fantastic"]]}, {"sent": ["Tiffany", "'s", "apartment", "space", "is", "the", "perfect", "spot", "if", "you", "'re", "staying", "in", "Boston", "."], "pred": [["the ambience", "Tiffany's apartment space", "positive", "perfect"]], "gold": [["the location overall", "tiffany's apartment", "positive", "perfect spot"]]}, {"sent": ["By", "far", "one", "of", "the", "best", "locations", "you", "could", "stay", "at", "in", "Boston", "."], "pred": [["the location", "it", "positive", "best"]], "gold": [["the location overall", "it", "positive", "one of the best"]]}, {"sent": ["Everything", "was", "super", "clean", "."], "pred": [["the ambience", "it", "positive", "clean"]], "gold": [["the hotel cleanliness", "null everything", "positive", "super clean"]]}, {"sent": ["Entry", "was", "simple", "and", "easy", "."], "pred": [["the service", "it", "positive", "simple"], ["the service", "it", "positive", "easy"]], "gold": [["the service overall", "entry", "positive", "simple and easy"]]}, {"sent": ["Great", "location", "close", "to", "the", "Commons", "."], "pred": [["the location", "location", "positive", "great"]], "gold": [["the location overall", "location", "positive", "great"]]}, {"sent": ["My", "hosts", "made", "me", "feel", "welcome", "the", "second", "I", "entered", "the", "home", ",", "helping", "me", "carry", "my", "items", "upstairs", ",", "explaining", "where", "everything", "was", "and", "offering", "me", "breakfast", "and", "coffee", "in", "the", "morning", "."], "pred": [["the service", "hosts", "positive", "welcome"]], "gold": [["the service overall", "hosts", "positive", "NULL"]]}, {"sent": ["This", "location", "does", "not", "have", "a", "kitchen", "and", "you", "must", "share", "a", "bathroom", "."], "pred": [["miscellaenous or anything else", "location", "negative", "NULL"]], "gold": [["the rooms features", "location", "negative", "NULL"]]}, {"sent": ["The", "hit", "was", "the", "rooftop", "which", "allowed", "for", "360", "degree", "views", "which", "was", "perfect", "for", "the", "70-80", "degree", "weather", "we", "were", "enjoying", "."], "pred": [["the location", "rooftop", "positive", "hit"]], "gold": [["the facilities features", "rooftop", "positive", "the hit"]]}, {"sent": ["I", "highly", "recommend", "it", "!"], "pred": [["the restaurant overall", "it", "positive", "recommend"]], "gold": [["the hotel overall", "it", "positive", "highly recommend"]]}, {"sent": ["Excellent", "location", "for", "exploring", "Boston", "."], "pred": [["the location", "location", "positive", "excellent"]], "gold": [["the location overall", "location", "positive", "excellent"]]}, {"sent": ["Best", "location", "in", "Boston", "."], "pred": [["the location", "location", "positive", "best"]], "gold": [["the location overall", "location", "positive", "best"]]}, {"sent": ["Great", "attention", "to", "detail", "and", "very", "good", "communication"], "pred": [["the service", "it", "positive", "good"], ["the service", "it", "positive", "great"]], "gold": [["the service quality", "communication", "positive", "very good"], ["the service quality", "it", "positive", "great attention to detail"]]}, {"sent": ["I", "enjoy", "dancing", "with", "these", "shoes", "on", "my", "feet", "."], "pred": [["the shoe quality", "shoes", "positive", "enjoy"]], "gold": [["the shoes overall", "shoes", "positive", "enjoy"]]}, {"sent": ["Super", "crinoline", "for", "the", "price", "!"], "pred": [["the food quality", "crinoline", "positive", "super"], ["the food prices", "crinoline", "positive", "super"]], "gold": [["the clothing prices", "crinoline", "positive", "super"]]}, {"sent": ["The", "transition", "option", "is", "nice", "too", "so", "you", "can", "wear", "them", "as", "leggings", "."], "pred": [["the fit", "transition option", "positive", "nice"]], "gold": [["the bottom options", "transition option", "positive", "nice"]]}, {"sent": ["They", "hold", "up", "great", "!"], "pred": [["the shoe quality", "it", "positive", "great"]], "gold": [["the clothing quality", "it", "positive", "great"]]}, {"sent": ["I", "have", "always", "worn", "LifeStride", "shoes", "but", "was", "disappointed", "when", "they", "were", "not", "leather", "and", "they", "were", "made", "in", "China", "."], "pred": [["the shoes quality", "shoes", "negative", "disappointed"]], "gold": [["the shoes brand", "lifestride shoes", "negative", "disappointed"]]}, {"sent": ["I", "use", "them", "for", "musical", "theatre", "productions", "and", "they", "holdup", "well", "."], "pred": [["the shoe quality", "it", "positive", "well"]], "gold": [["the clothing quality", "it", "positive", "well"]]}, {"sent": ["She", "said", "they", "are", "so", "comfortable", ",", "and", "they", "are", "perfect", "."], "pred": [["the fit", "it", "positive", "comfortable"], ["the fit", "it", "positive", "perfect"]], "gold": [["the clothing quality", "it", "positive", "so comfortable"], ["the clothing overall", "it", "positive", "perfect"]]}, {"sent": ["They", "slot", "over", "the", "abdomen", "as", "I", "was", "putting", "them", "on", "very", "carefully", "this", "morning", "-could", "not", "wear", "them", ",", "will", "return", "."], "pred": [["the fit", "it", "negative", "NULL"]], "gold": [["the clothing overall", "it", "negative", "NULL"]]}, {"sent": ["These", "are", "the", "most", "comfortable", "shoes", "I", "'ve", "ever", "worn", ",", "and", "they", "'re", "stylish", "."], "pred": [["the comfort", "shoes", "positive", "comfortable"], ["the style", "shoes", "positive", "stylish"]], "gold": [["the shoes quality", "shoes", "positive", "most comfortable"], ["the shoes looking", "shoes", "positive", "stylish"]]}, {"sent": ["I", "bought", "2", "other", "pairs", "for", "other", "cast", "members", "!"], "pred": [["the shoe quality", "it", "positive", "NULL"]], "gold": [["the clothing overall", "it", "positive", "NULL"]]}, {"sent": ["Comfortable", "and", "attractive", "."], "pred": [["the ambience", "it", "positive", "comfortable"], ["the ambience", "it", "positive", "attractive"]], "gold": [["the clothing looking", "it", "positive", "attractive"], ["the clothing quality", "it", "positive", "comfortable"]]}, {"sent": ["Everything", "else", "about", "these", "tights", "is", "amazing", "."], "pred": [["the fit", "tights", "positive", "amazing"]], "gold": [["the bottom overall", "tights", "positive", "amazing"]]}, {"sent": ["These", "shoes", "are", "great", "."], "pred": [["the shoe quality", "shoes", "positive", "great"]], "gold": [["the shoes overall", "shoes", "positive", "great"]]}, {"sent": ["Although", "the", "tights", "make", "the", "legs", "look", "beautiful", ",", "I", "have", "noticed", "the", "the", "seams", "are", "coming", "apart", "at", "the", "crotch", "."], "pred": [["the fit", "tights", "positive", "beautiful"], ["the fit", "seams", "negative", "coming apart"]], "gold": [["the bottom looking", "tights", "positive", "NULL"], ["the bottom quality", "seams", "negative", "NULL"]]}, {"sent": ["They", "are", "nice", "and", "exactly", "what", "I", "expected", "."], "pred": [["the food quality", "it", "positive", "nice"], ["the food quality", "it", "positive", "exactly what I expected"]], "gold": [["the clothing overall", "it", "positive", "nice"]]}, {"sent": ["My", "husband", "loves", "his", "boots", ",", "excellent", "quality", "."], "pred": [["the boot quality", "boots", "positive", "excellent"]], "gold": [["the shoes quality", "boots", "positive", "loves"]]}, {"sent": ["Very", "small", "fit", "."], "pred": [["the ambience", "fit", "negative", "small"]], "gold": [["the clothing size", "it", "negative", "very small fit"]]}, {"sent": ["Follow", "the", "capezio", "size", "chart", "and", "you", "'re", "in", "the", "clear", "."], "pred": [["the food styles and options", "capezio size chart", "positive", "NULL"]], "gold": [["the clothing size", "capezio size chart", "positive", "in the clear"]]}, {"sent": ["The", "soles", "are", "soft", "too", "."], "pred": [["the fit", "soles", "positive", "soft"]], "gold": [["the shoes quality", "soles", "positive", "soft"]]}, {"sent": ["Order", "1", "size", "larger", "than", "needed", "."], "pred": [["the food styles and options", "it", "negative", "NULL"]], "gold": [["the clothing size", "it", "negative", "NULL"]]}, {"sent": ["Great", "for", "Programming", "and", "for", "low", "end", "gaming"], "pred": [["miscellaenous or anything else", "it", "positive", "great"]], "gold": [["the computer performance", "it", "positive", "great"]]}, {"sent": ["The", "combination", "of", "these", "design", "flows", "leads", "to", "broken", "displays", "when", "the", "magsafe", "plug", "is", "caught", "inside", "the", "computer", "upon", "closing", ",", "breaking", "the", "monitor", "."], "pred": [["the service", "it", "negative", "broken"]], "gold": [["the hardware features", "design", "negative", "flows"]]}, {"sent": ["Images", "are", "too", "dark", "and", "blurry", "."], "pred": [["the ambience", "images", "negative", "dark"], ["the ambience", "images", "negative", "blurry"]], "gold": [["the display quality", "images", "negative", "too dark and blurry"]]}, {"sent": ["I", "got", "it", "mainly", "to", "do", "android", "app", "development", ",", "and", "let", "me", "tell", "you", ",", "it", "'s", "worth", "more", "than", "it", "'s", "price", "."], "pred": [["the product overall", "it", "positive", "worth"], ["the product's prices", "it", "positive", "worth"]], "gold": [["the computer price", "it", "positive", "worth more than it's price"]]}, {"sent": ["I", "'m", "a", "mac", "user", "and", "I", "would", "love", "to", "get", "this", "laptop", "."], "pred": [["the laptop overall", "laptop", "positive", "love"]], "gold": [["the laptop overall", "laptop", "positive", "love to get this"]]}, {"sent": ["Keyboard", ":", "it", "is", "all", "mushy", "no", "tactile", "feedback", "."], "pred": [["the keyboard", "keyboard", "negative", "mushy"]], "gold": [["the keyboard features", "keyboard", "negative", "mushy"]]}, {"sent": ["For", "the", "price", "you", "can", "not", "go", "wrong", ",", "especially", "having", "an", "8th", "gen", "Intel", "processor", "."], "pred": [["the processor", "it", "positive", "8th gen"], ["the computer's prices", "it", "positive", "wrong"]], "gold": [["the computer price", "it", "positive", "can not go wrong"]]}, {"sent": ["It", "'s", "very", "well", "made", "-", "solid", "construction", "and", "a", "comfortable", ",", "well-sized", "keyboard", "."], "pred": [["the product quality", "it", "positive", "well made"], ["the build quality", "construction", "positive", "solid"], ["the ergonomics", "keyboard", "positive", "comfortable"], ["the layout", "keyboard", "positive", "well-sized"]], "gold": [["the computer features", "it", "positive", "well made"], ["the keyboard usability", "keyboard", "positive", "comfortable"]]}, {"sent": ["Camera", "and", "microphone", "are", "both", "high", "enough", "quality", "for", "discord/google", "hangouts/etc", "."], "pred": [["the audio quality", "microphone", "positive", "high enough quality"], ["the image quality", "camera", "positive", "high enough quality"]], "gold": [["the multimedia_device quality", "camera", "positive", "high enough quality"], ["the multimedia_device quality", "microphone", "positive", "high enough quality"]]}, {"sent": ["It", "has", "a", "nice", "keyboard", "touch", "."], "pred": [["the layout", "keyboard touch", "positive", "nice"]], "gold": [["the keyboard usability", "it", "positive", "NULL"]]}, {"sent": ["Please", "do", "not", "purchase", "this", "computer", ",", "it", "performs", "worse", "than", "the", "$", "200", "computer", "I", "used", "while", "waiting", "on", "the", "'", "replacement", "'", "computer", "I", "got", "when", "the", "other", "one", "crashed", "."], "pred": [["the computer overall", "computer", "negative", "worse"]], "gold": [["the computer performance", "computer", "negative", "performs worse"]]}, {"sent": ["It", "took", "a", "few", "weeks", "for", "them", "to", "send", "it", "back", "."], "pred": [["the service", "it", "negative", "NULL"]], "gold": [["the shipping overall", "it", "negative", "NULL"]]}, {"sent": ["I", "have", "gone", "through", "all", "the", "troubleshooting", "steps", "and", "still", "nothing", "."], "pred": [["the service", "it", "negative", "NULL"]], "gold": [["the support quality", "it", "negative", "NULL"]]}, {"sent": ["Even", "without", "a", "SSD", ",", "it", "is", "still", "pretty", "fast", "."], "pred": [["the performance", "it", "positive", "fast"]], "gold": [["the computer performance", "it", "positive", "pretty fast"]]}, {"sent": ["I", "really", "liked", "the", "laptop", "for", "its", "sleekness", "and", "weight", "."], "pred": [["the design", "laptop", "positive", "sleekness"], ["the laptop's weight", "laptop", "positive", "liked"]], "gold": [["the laptop features", "sleekness and weight", "positive", "really liked"]]}, {"sent": ["Delivery", "-", "very", "fast", "by", "courier", "."], "pred": [["the service", "courier", "positive", "fast"]], "gold": [["the shipping overall", "delivery", "positive", "very fast"]]}, {"sent": ["This", "laptop", "is", "verry", "good", ",", "the", "screen", "is", "not", "the", "best", "but", "its", "good", "for", "the", "price", ",", "its", "a", "cheap", "gaming", "laptop", "and", "works", "with", "every", "game", "i", "trow", "at", "it", ":", "-", ")"], "pred": [["the laptop overall", "laptop", "positive", "good"], ["the display", "screen", "negative", "not the best"], ["the laptop's prices", "laptop", "positive", "good"], ["the performance", "it", "positive", "cheap"], ["the performance", "it", "positive", "works"]], "gold": [["the laptop overall", "laptop", "positive", "verry good"], ["the display quality", "screen", "positive", "not the best but its good for the price"], ["the laptop price", "price", "positive", "cheap"]]}, {"sent": ["Laptop", "was", "new", ",", "in", "perfect", "condition", "and", "works", "like", "a", "charm", "."], "pred": [["the computer overall", "laptop", "positive", "new"], ["the condition", "laptop", "positive", "perfect"]], "gold": [["the laptop overall", "laptop", "neutral", "new"], ["the laptop quality", "condition", "positive", "perfect"]]}, {"sent": ["I", "had", "hoped", "for", "better", "battery", "life", ",", "as", "it", "had", "only", "about", "2-1/2", "hours", "doing", "heavy", "computations", "(", "8", "threads", "using", "100", "%", "of", "the", "CPU", ")", "."], "pred": [["the battery life", "battery life", "negative", "NULL"]], "gold": [["the battery performance", "battery life", "negative", "hoped for better"]]}, {"sent": ["Feel", "really", "disappointed", "as", "was", "so", "happy", "with", "previous", "model", "."], "pred": [["the food quality", "it", "negative", "disappointed"]], "gold": [["the computer overall", "it", "negative", "really disappointed"], ["the computer overall", "previous model", "positive", "so happy"]]}, {"sent": ["Weird", ",", "but", "whatever", ",", "I", "need", "to", "eat", "regardless", "of", "the", "coupon.We", "waited", "for", "what", "seemed", "like", "an", "incredibly", "long", "time", "just", "to", "get", "our", "food", "."], "pred": [["the service", "it", "negative", "NULL"]], "gold": [["the service quality", "it", "negative", "NULL"]]}, {"sent": ["I", "come", "here", "because", "you", "leave", "full", "and", "with", "money", "still", "in", "your", "pockets", "."], "pred": [["the restaurant overall", "it", "positive", "NULL"]], "gold": [["the restaurant prices", "money", "positive", "NULL"]]}, {"sent": ["I", "love", "hot", "pot", "but", "the", "service", "just", "makes", "things", "bad", "here", "."], "pred": [["the food quality", "hot pot", "positive", "love"], ["the service", "service", "negative", "bad"]], "gold": [["the food quality", "hot pot", "positive", "love"], ["the service overall", "service", "negative", "bad"]]}, {"sent": ["I", "do", "n't", "usually", "order", "PhO", "(", "I", "do", "n't", "think", "I", "do", "at", "all", "because", "my", "mom", "is", "a", "great", "Pho", "cooker", ")", ",", "yet", "this", "place", "makes", "me", "wanting", "Pho", "every", "time", "I", "come", "."], "pred": [["the food quality", "Pho", "positive", "NULL"]], "gold": [["the food quality", "pho", "positive", "NULL"]]}, {"sent": ["This", "is", "one", "of", "my", "favorite", "brunch", "places", "."], "pred": [["the restaurant overall", "it", "positive", "favorite"]], "gold": [["the restaurant overall", "brunch places", "positive", "favorite"]]}, {"sent": ["Other", "establishments", "on", "the", "North", "End", "spoil", "you", "with", "tasty", "oils", "and", "fresh", "bread", "...", "that", "'s", "a", "big", "miss", "here", "!"], "pred": [["the food quality", "bread", "negative", "fresh"], ["the food quality", "oils", "negative", "tasty"]], "gold": [["the food quality", "fresh bread", "negative", "big miss"], ["the food quality", "tasty oils", "negative", "big miss"]]}, {"sent": ["Im", "going", "to", "have", "to", "come", "back", "here", "to", "try", "the", "food", ",", "so", "this", "review", "is", "just", "for", "the", "drinks", ",", "service", "and", "atmosphere.The", "atmosphere", "is", "great", ",", "nothing", "is", "too", "overwhelming", "and", "it", "does", "n't", "seem", "like", "they", "'re", "trying", "to", "beat", "you", "over", "the", "head", "with", "a", "theme", "in", "the", "decorating", "."], "pred": [["the drink quality", "drinks", "positive", "great"], ["the service", "service", "positive", "great"], ["the ambience", "atmosphere", "positive", "great"]], "gold": [["the ambience styles and options", "atmosphere", "positive", "NULL"], ["the ambience overall", "atmosphere", "positive", "great"]]}, {"sent": ["This", "will", "probably", "be", "the", "last", "time", "we", "will", "come", "here", "."], "pred": [["the restaurant overall", "it", "negative", "NULL"]], "gold": [["the restaurant overall", "it", "negative", "NULL"]]}, {"sent": ["Stop", "driving", "out", "the", "wrong", "way", ",", "idiots.No", "credit", "cards", ",", "which", "is", "a", "bummer", ",", "but", "they", "do", "have", "an", "ATM", "inside", "."], "pred": [["the restaurant overall", "it", "negative", "NULL"]], "gold": [["the service miscellaneous", "credit cards", "negative", "bummer"], ["the service miscellaneous", "atm", "positive", "NULL"]]}, {"sent": ["So", ",", "while", "I", "would", "n't", "quite", "recommend", "it", "for", "date", "night", "or", "a", "rehearsal", "dinner", ",", "it", "'s", "plenty", "acceptable", "for", "grabbing", "a", "quick", "lunch", "or", "dinner", "on", "your", "way", "somewhere", "else", "."], "pred": [["miscellaenous or anything else", "it", "neutral", "acceptable"]], "gold": [["the restaurant overall", "it", "negative", "wouldn't quite recommend"], ["the restaurant overall", "it", "positive", "plenty acceptable"]]}, {"sent": ["Went", "to", "breakfast", "with", "my", "bestie", "here", "and", "really", "enjoyed", "the", "country", "style", "breakfast", "and", "ambiance.", "They", "were", "pretty", "crowded", "for", "a", "weekday", "and", "our", "server", "ladies", "were", "really", "sweet", "and", "helpful", "."], "pred": [["the food quality", "country style breakfast", "positive", "enjoyed"], ["the ambience", "ambiance", "positive", "enjoyed"], ["the ambience", "server ladies", "positive", "sweet"], ["the service", "server ladies", "positive", "helpful"]], "gold": [["the ambience overall", "ambiance", "positive", "really enjoyed"], ["the food styles and options", "country style breakfast", "positive", "really enjoyed"], ["the service quality", "server ladies", "positive", "really sweet and helpful"]]}, {"sent": ["Great", "place", "!"], "pred": [["the restaurant overall", "place", "positive", "great"]], "gold": [["the restaurant overall", "place", "positive", "great"]]}, {"sent": ["My", "advice", "to", "the", "owners", ":", "Walking", "by", "on", "E.", "Hastings", ",", "it", "'s", "easy", "to", "miss", "this", "spot", "."], "pred": [["the restaurant overall", "spot", "negative", "miss"]], "gold": [["the location overall", "spot", "negative", "easy to miss"]]}, {"sent": ["The", "reason", "why", "I", "gave", "3", "stars", "is", "because", "we", "had", "to", "search", "for", "our", "waitress", "and", "it", "took", "about", "a", "hour", "before", "we", "receive", "our", "food", "."], "pred": [["the service", "waitress", "negative", "NULL"]], "gold": [["the service miscellaneous", "waitress", "negative", "3 stars"]]}, {"sent": ["To", "add", "more", "insult", "he", "added", "a", "splash", "of", "coke", "to", "our", "drinks", "...", "..I", "'m", "a", "relatively", "calm", "guy", "."], "pred": [["the service", "it", "negative", "insult"]], "gold": [["the service miscellaneous", "it", "negative", "add more insult"]]}, {"sent": ["The", "old", "place", "was", "more", "accommodating", "to", "singles", "."], "pred": [["miscellaenous or anything else", "place", "positive", "accommodating"]], "gold": [["the restaurant overall", "old place", "positive", "more accommodating"]]}, {"sent": ["This", "chicken", "is", "unbelievable", "."], "pred": [["the food quality", "chicken", "positive", "unbelievable"]], "gold": [["the food overall", "chicken", "positive", "unbelievable"]]}, {"sent": ["The", "chicken", "was", "also", "overcooked", "and", "dry", "."], "pred": [["the food quality", "chicken", "negative", "overcooked"], ["the food quality", "chicken", "negative", "dry"]], "gold": [["the food quality", "chicken", "negative", "overcooked and dry"]]}, {"sent": ["I", "was", "reluctant", "to", "go", "here", "."], "pred": [["the restaurant overall", "it", "negative", "reluctant"]], "gold": [["the restaurant overall", "it", "neutral", "reluctant"]]}, {"sent": ["Amazing", "turkey", "burger", ",", "french", "fries", "are", "to", "die", "for", ",", "and", "dont", "even", "get", "me", "STARTED", "on", "the", "milkshakes", "."], "pred": [["the food quality", "turkey burger", "positive", "amazing"], ["the food quality", "french fries", "positive", "die for"], ["the food quality", "milkshakes", "positive", "NULL"]], "gold": [["the food quality", "turkey burger", "positive", "amazing"], ["the food quality", "french fries", "positive", "to die for"], ["the drinks quality", "milkshakes", "positive", "NULL"]]}]